{
  "version": "5.0.1",
  "flags": {},
  "shapes": [
    {
      "label": "filament",
      "points": [
        [
          46,
          36
        ],
        [
          45,
          37
        ],
        [
          41,
          37
        ],
        [
          41,
          41
        ],
        [
          42,
          41
        ],
        [
          43,
          42
        ],
        [
          43,
          43
        ],
        [
          45,
          45
        ],
        [
          45,
          48
        ],
        [
          47,
          50
        ],
        [
          47,
          51
        ],
        [
          48,
          51
        ],
        [
          49,
          52
        ],
        [
          49,
          53
        ],
        [
          50,
          54
        ],
        [
          51,
          54
        ],
        [
          52,
          55
        ],
        [
          52,
          57
        ],
        [
          55,
          60
        ],
        [
          55,
          61
        ],
        [
          58,
          64
        ],
        [
          58,
          66
        ],
        [
          59,
          67
        ],
        [
          59,
          70
        ],
        [
          60,
          71
        ],
        [
          60,
          72
        ],
        [
          61,
          73
        ],
        [
          61,
          76
        ],
        [
          62,
          77
        ],
        [
          63,
          77
        ],
        [
          64,
          78
        ],
        [
          64,
          80
        ],
        [
          65,
          80
        ],
        [
          68,
          83
        ],
        [
          68,
          86
        ],
        [
          73,
          86
        ],
        [
          75,
          84
        ],
        [
          75,
          78
        ],
        [
          74,
          77
        ],
        [
          74,
          76
        ],
        [
          73,
          75
        ],
        [
          72,
          75
        ],
        [
          69,
          72
        ],
        [
          69,
          71
        ],
        [
          64,
          66
        ],
        [
          64,
          64
        ],
        [
          63,
          64
        ],
        [
          62,
          63
        ],
        [
          62,
          61
        ],
        [
          61,
          61
        ],
        [
          60,
          60
        ],
        [
          60,
          57
        ],
        [
          58,
          55
        ],
        [
          58,
          53
        ],
        [
          56,
          51
        ],
        [
          56,
          45
        ],
        [
          55,
          44
        ],
        [
          53,
          44
        ],
        [
          52,
          43
        ],
        [
          52,
          40
        ],
        [
          50,
          40
        ],
        [
          49,
          39
        ],
        [
          49,
          37
        ],
        [
          48,
          36
        ]
      ],
      "group_id": null,
      "shape_type": "polygon",
      "flags": {}
    }
  ],
  "imagePath": "oscillation-2_t17c1.tif",
  "imageData": null,
  "imageHeight": 115,
  "imageWidth": 115
}